[{"text": "u", "sender": "useradmin", "time": "18:45", "date": "24-06-2023", "room": "1"}, {"text": "v", "sender": "useradmin", "time": "18:45", "date": "24-06-2023", "room": "1"}, {"text": "w", "sender": "useradmin", "time": "18:45", "date": "24-06-2023", "room": "1"}, {"text": "x", "sender": "useradmin", "time": "18:45", "date": "24-06-2023", "room": "1"}, {"text": "y", "sender": "useradmin", "time": "18:45", "date": "24-06-2023", "room": "1"}, {"text": "z", "sender": "useradmin", "time": "18:45", "date": "24-06-2023", "room": "1"}]